aio_auth_with-0.0.4.dist-info/DESCRIPTION.rst
aio_auth_with-0.0.4.dist-info/METADATA
aio_auth_with-0.0.4.dist-info/RECORD
aio_auth_with-0.0.4.dist-info/WHEEL
aio_auth_with-0.0.4.dist-info/entry_points.txt
aio_auth_with-0.0.4.dist-info/metadata.json
aio_auth_with-0.0.4.dist-info/top_level.txt
auth_with/__init__.py
auth_with/github.py
auth_with/http.py
builder/__init__.py
builder/__main__.py
builder/cli/__init__.py
