Metadata-Version: 2.0
Name: aio-auth-with
Version: 0.0.4
Summary: UNKNOWN
Home-page: https://github.com/feluxe/aio-auth-with
Author: Felix Meyer-Wolters
Author-email: felix@meyerwolters.de
License: unlicensed
Download-URL: https://github.com/feluxe/aio-auth-with/tarball/0.0.4
Platform: 
Requires-Dist: aiohttp
